[
  {
    "id": 1,
    "title": "NCERT Class 10 Complete Package",
    "description": "Complete set of NCERT textbooks for Class 10 - All subjects including Science, Mathematics, Social Science, English and Hindi",
    "applicable_classes": ["10"],
    "subjects": ["Mathematics", "Science", "Social Science", "English", "Hindi"],
    "type": "textbook",
    "format": "PDF",
    "size": "120 MB",
    "downloads": 15420,
    "rating": 4.8,
    "free": true,
    "download_link": "https://ncert.nic.in/textbook.php?jemh1=0-8",
    "preview_link": "https://ncert.nic.in/textbook.php?jemh1=0-8",
    "category": "Official Textbooks",
    "language": ["English", "Hindi"],
    "last_updated": "2024-04-15",
    "publisher": "NCERT",
    "tags": ["cbse", "ncert", "class10", "official"]
  },
  {
    "id": 2,
    "title": "NCERT Class 12 Science Stream Books",
    "description": "Physics, Chemistry, Biology and Mathematics textbooks for Class 12 CBSE students",
    "applicable_classes": ["12"],
    "subjects": ["Physics", "Chemistry", "Biology", "Mathematics"],
    "type": "textbook",
    "format": "PDF",
    "size": "180 MB",
    "downloads": 23150,
    "rating": 4.9,
    "free": true,
    "download_link": "https://ncert.nic.in/textbook.php?lelm1=0-12",
    "preview_link": "https://ncert.nic.in/textbook.php?lelm1=0-12",
    "category": "Science Textbooks",
    "language": ["English", "Hindi"],
    "last_updated": "2024-04-15",
    "publisher": "NCERT",
    "tags": ["cbse", "ncert", "class12", "pcm", "pcb"]
  },
  {
    "id": 3,
    "title": "Career Guidance After Class 10",
    "description": "Comprehensive guide covering all stream options after Class 10 - Science PCM/PCB, Commerce, Arts with detailed career paths",
    "applicable_classes": ["10"],
    "subjects": ["Career Guidance"],
    "type": "guide",
    "format": "PDF",
    "size": "25 MB",
    "downloads": 8750,
    "rating": 4.7,
    "free": true,
    "download_link": "#",
    "preview_link": "#",
    "category": "Career Guidance",
    "language": ["English", "Hindi"],
    "last_updated": "2024-08-20",
    "publisher": "Career Counseling Board",
    "tags": ["career", "streams", "guidance", "class10"]
  },
  {
    "id": 4,
    "title": "JEE Main Preparation Materials",
    "description": "Complete study package for JEE Main including previous year papers, mock tests, and subject-wise practice materials",
    "applicable_classes": ["11", "12"],
    "subjects": ["Physics", "Chemistry", "Mathematics"],
    "type": "preparation_material",
    "format": "PDF + Online Tests",
    "size": "300 MB",
    "downloads": 45230,
    "rating": 4.8,
    "free": true,
    "download_link": "#",
    "preview_link": "#",
    "category": "Entrance Exam Preparation",
    "language": ["English"],
    "last_updated": "2024-09-01",
    "publisher": "National Testing Agency",
    "tags": ["jee", "entrance", "engineering", "pcm"]
  },
  {
    "id": 5,
    "title": "NEET Biology Study Materials",
    "description": "Comprehensive Biology study materials for NEET preparation with diagrams, practice questions and previous year solutions",
    "applicable_classes": ["11", "12"],
    "subjects": ["Biology"],
    "type": "preparation_material",
    "format": "PDF",
    "size": "85 MB",
    "downloads": 32100,
    "rating": 4.9,
    "free": true,
    "download_link": "#",
    "preview_link": "#",
    "category": "Medical Entrance Preparation",
    "language": ["English"],
    "last_updated": "2024-08-25",
    "publisher": "Medical Council of India",
    "tags": ["neet", "biology", "medical", "pcb"]
  },
  {
    "id": 6,
    "title": "Commerce Stream Career Options",
    "description": "Detailed guide about careers in Commerce - CA, CS, BBA, Economics, Banking, Finance and more with salary insights",
    "applicable_classes": ["10", "11", "12"],
    "subjects": ["Commerce", "Career Guidance"],
    "type": "guide",
    "format": "PDF",
    "size": "15 MB",
    "downloads": 12450,
    "rating": 4.6,
    "free": true,
    "download_link": "#",
    "preview_link": "#",
    "category": "Career Guidance",
    "language": ["English", "Hindi"],
    "last_updated": "2024-07-30",
    "publisher": "Commerce Education Board",
    "tags": ["commerce", "career", "business", "finance"]
  },
  {
    "id": 7,
    "title": "Arts & Humanities Career Guide",
    "description": "Comprehensive career guide for Arts stream students - Civil Services, Law, Journalism, Psychology, Literature and creative fields",
    "applicable_classes": ["10", "11", "12"],
    "subjects": ["Arts", "Humanities", "Career Guidance"],
    "type": "guide",
    "format": "PDF",
    "size": "20 MB",
    "downloads": 9850,
    "rating": 4.5,
    "free": true,
    "download_link": "#",
    "preview_link": "#",
    "category": "Career Guidance",
    "language": ["English", "Hindi"],
    "last_updated": "2024-08-10",
    "publisher": "Humanities Education Council",
    "tags": ["arts", "humanities", "upsc", "law"]
  },
  {
    "id": 8,
    "title": "Vedantu Class 10 Study Materials",
    "description": "Free study materials from Vedantu including revision notes, important questions, and sample papers for all subjects",
    "applicable_classes": ["10"],
    "subjects": ["Mathematics", "Science", "English", "Hindi", "Social Science"],
    "type": "study_notes",
    "format": "PDF + Videos",
    "size": "150 MB",
    "downloads": 28700,
    "rating": 4.7,
    "free": true,
    "download_link": "https://vedantu.com/study-material",
    "preview_link": "https://vedantu.com/study-material",
    "category": "Study Materials",
    "language": ["English", "Hindi"],
    "last_updated": "2024-09-05",
    "publisher": "Vedantu",
    "tags": ["vedantu", "notes", "class10", "cbse"]
  },
  {
    "id": 9,
    "title": "Digital India E-Pathshala Resources",
    "description": "Government initiative providing free textbooks, audio, video, and interactive content for classes 1-12",
    "applicable_classes": ["10", "11", "12"],
    "subjects": ["All Subjects"],
    "type": "multimedia",
    "format": "PDF + Audio + Video",
    "size": "500+ MB",
    "downloads": 75000,
    "rating": 4.8,
    "free": true,
    "download_link": "https://epathshala.nic.in",
    "preview_link": "https://epathshala.nic.in",
    "category": "Government Resources",
    "language": ["English", "Hindi", "Regional"],
    "last_updated": "2024-09-01",
    "publisher": "Government of India",
    "tags": ["government", "epathshala", "free", "official"]
  },
  {
    "id": 10,
    "title": "Skill Development Programs Guide",
    "description": "Information about vocational training, skill development courses, and alternative career paths after 10th and 12th",
    "applicable_classes": ["10", "12"],
    "subjects": ["Skill Development", "Vocational Training"],
    "type": "guide",
    "format": "PDF",
    "size": "30 MB",
    "downloads": 6420,
    "rating": 4.4,
    "free": true,
    "download_link": "#",
    "preview_link": "#",
    "category": "Skill Development",
    "language": ["English", "Hindi"],
    "last_updated": "2024-08-15",
    "publisher": "Skill Development Ministry",
    "tags": ["skills", "vocational", "training", "employment"]
  },
  {
    "id": 11,
    "title": "State Board Study Materials",
    "description": "Study materials for various state boards including UP Board, Bihar Board, Maharashtra Board, and others",
    "applicable_classes": ["10", "12"],
    "subjects": ["Mathematics", "Science", "English", "Hindi"],
    "type": "textbook",
    "format": "PDF",
    "size": "200 MB",
    "downloads": 18900,
    "rating": 4.3,
    "free": true,
    "download_link": "#",
    "preview_link": "#",
    "category": "State Board Resources",
    "language": ["English", "Hindi", "Regional"],
    "last_updated": "2024-08-30",
    "publisher": "Various State Boards",
    "tags": ["state", "regional", "board", "local"]
  },
  {
    "id": 12,
    "title": "English Language Improvement Kit",
    "description": "Comprehensive English language learning materials including grammar, vocabulary, reading comprehension, and speaking skills",
    "applicable_classes": ["10", "11", "12"],
    "subjects": ["English"],
    "type": "language_learning",
    "format": "PDF + Audio",
    "size": "120 MB",
    "downloads": 22100,
    "rating": 4.6,
    "free": true,
    "download_link": "#",
    "preview_link": "#",
    "category": "Language Learning",
    "language": ["English"],
    "last_updated": "2024-08-20",
    "publisher": "English Language Institute",
    "tags": ["english", "language", "grammar", "vocabulary"]
  }
]